polygon_neighbours.cpython-310-x86_64-linux-gnu.so
polygon_neighbours-1.2.dist-info/top_level.txt
polygon_neighbours-1.2.dist-info/RECORD
polygon_neighbours-1.2.dist-info/WHEEL
polygon_neighbours-1.2.dist-info/METADATA
polygon_neighbours-1.2.dist-info/LICENSE
